ts3ekkoclient/__init__.py
ts3ekkoclient/argparser.py
ts3ekkoclient/bot.py
ts3ekkoclient/command.py
ts3ekkoclient/entrypoint.py
ts3ekkoclient/errors.py
ts3ekkoclient/event_type.py
ts3ekkoclient/models.py
ts3ekkoclient/permission.py
ts3ekkoclient/ts3ekko.py
ts3ekkoclient/ts3identity.py
ts3ekkoclient/webhooks.py
ts3ekkoclient/cogs/__init__.py
ts3ekkoclient/cogs/media.py
ts3ekkoclient/cogs/text.py
ts3ekkoclient-0.0.11.dist-info/DESCRIPTION.rst
ts3ekkoclient-0.0.11.dist-info/METADATA
ts3ekkoclient-0.0.11.dist-info/RECORD
ts3ekkoclient-0.0.11.dist-info/WHEEL
ts3ekkoclient-0.0.11.dist-info/entry_points.txt
ts3ekkoclient-0.0.11.dist-info/metadata.json
ts3ekkoclient-0.0.11.dist-info/top_level.txt
