Metadata-Version: 2.0
Name: ts3ekkoclient
Version: 0.0.11
Summary: ts3ekkoclient
Home-page: https://gitlab.com/networkjanitor/ts3ekkoclient
Author: Xyoz Netsphere
Author-email: nanoowl@xyooz.net
License: MIT
Platform: UNKNOWN
Classifier: Development Status :: 3 - Alpha
Classifier: License :: OSI Approved :: MIT License
Classifier: Programming Language :: Python :: 3
Classifier: Programming Language :: Python :: 3.6
Requires-Dist: SQLAlchemy
Requires-Dist: SQLAlchemy-utils
Requires-Dist: psycopg2
Requires-Dist: ts3query
Requires-Dist: bottle
Requires-Dist: ts3ekkoutil (>=0.0.19)
Requires-Dist: requests
Requires-Dist: python-mpv
Requires-Dist: youtube-dl
Requires-Dist: sphinx
Requires-Dist: sphinx-autobuild
Requires-Dist: sphinx-rtd-theme
Requires-Dist: alchemy-mock
